MANIFEST.in
Makefile
README.rst
VERSION
requirements.txt
setup.cfg
setup.py
test_requirements.txt
charms/__init__.py
charms.templating.jinja2.egg-info/PKG-INFO
charms.templating.jinja2.egg-info/SOURCES.txt
charms.templating.jinja2.egg-info/dependency_links.txt
charms.templating.jinja2.egg-info/requires.txt
charms.templating.jinja2.egg-info/top_level.txt
charms/templating/__init__.py
charms/templating/jinja2.py