Metadata-Version: 1.0
Name: charms.templating.jinja2
Version: 1.0.1
Summary: Framework for writing reactive-style Juju Charms
Home-page: https://github.com/juju-solutions/charms.templating.jinja2
Author: Cory Johns
Author-email: johnsca@gmail.com
License: Apache License 2.0
Platform: UNKNOWN
